examples/__init__.py
examples/example_models_convert.py
myoconverter/O2MPipeline.py
myoconverter/__init__.py
myoconverter/conversion_steps/O2MStep1.py
myoconverter/conversion_steps/O2MStep2.py
myoconverter/conversion_steps/O2MStep3.py
myoconverter/conversion_steps/O2MSteps.py
myoconverter/conversion_steps/__init__.py
myoconverter/utils/__init__.py
myoconverter/utils/generate_pdf.py
myoconverter/xml/__init__.py
myoconverter/xml/config.py
myoconverter/xml/converter.py
myoconverter/xml/parsers.py
myoconverter/xml/utils.py
myoconverter/xml/bodies/Body.py
myoconverter/xml/bodies/Ground.py
myoconverter/xml/bodies/__init__.py
myoconverter/xml/bodies/utils.py
myoconverter/xml/constraints/CoordinateCouplerConstraint.py
myoconverter/xml/constraints/__init__.py
myoconverter/xml/forces/BushingForce.py
myoconverter/xml/forces/CoordinateActuator.py
myoconverter/xml/forces/CoordinateLimitForce.py
myoconverter/xml/forces/FunctionBasedBushingForce.py
myoconverter/xml/forces/Ligament.py
myoconverter/xml/forces/Millard2012EquilibriumMuscle.py
myoconverter/xml/forces/Muscle.py
myoconverter/xml/forces/PointActuator.py
myoconverter/xml/forces/Schutte1993Muscle_Deprecated.py
myoconverter/xml/forces/SpringGeneralizedForce.py
myoconverter/xml/forces/Thelen2003Muscle.py
myoconverter/xml/forces/TorqueActuator.py
myoconverter/xml/forces/__init__.py
myoconverter/xml/forces/utils.py
myoconverter/xml/joints/CustomJoint.py
myoconverter/xml/joints/Joint.py
myoconverter/xml/joints/PinJoint.py
myoconverter/xml/joints/SliderJoint.py
myoconverter/xml/joints/UniversalJoint.py
myoconverter/xml/joints/WeldJoint.py
myoconverter/xml/joints/__init__.py
myoconverter/xml/joints/utils.py
myoconverter/xml/markers/Marker.py
myoconverter/xml/markers/__init__.py
myoconverter/xml/path_points/ConditionalPathPoint.py
myoconverter/xml/path_points/MovingPathPoint.py
myoconverter/xml/path_points/PathPoint.py
myoconverter/xml/path_points/__init__.py
myoconverter/xml/path_points/utils.py
myoconverter-0.0.2.dist-info/LICENSE
myoconverter-0.0.2.dist-info/METADATA
myoconverter-0.0.2.dist-info/WHEEL
myoconverter-0.0.2.dist-info/top_level.txt
myoconverter-0.0.2.dist-info/RECORD
